odoo/addons/project_subtask_default_display_project/README.rst
odoo/addons/project_subtask_default_display_project/__init__.py
odoo/addons/project_subtask_default_display_project/__manifest__.py
odoo/addons/project_subtask_default_display_project/readme/CONFIGURE.md
odoo/addons/project_subtask_default_display_project/readme/CONTRIBUTORS.md
odoo/addons/project_subtask_default_display_project/readme/DESCRIPTION.md
odoo/addons/project_subtask_default_display_project/static/description/icon.png
odoo/addons/project_subtask_default_display_project/static/description/index.html
odoo/addons/project_subtask_default_display_project/tests/__init__.py
odoo/addons/project_subtask_default_display_project/tests/test_project_subtask_default_display_project.py
odoo/addons/project_subtask_default_display_project/views/project_task_views.xml
odoo_addon_project_subtask_default_display_project-16.0.1.1.0.1.dist-info/METADATA
odoo_addon_project_subtask_default_display_project-16.0.1.1.0.1.dist-info/WHEEL
odoo_addon_project_subtask_default_display_project-16.0.1.1.0.1.dist-info/top_level.txt
odoo_addon_project_subtask_default_display_project-16.0.1.1.0.1.dist-info/RECORD
