Metadata-Version: 2.1
Name: odoo-addon-project_subtask_default_display_project
Version: 16.0.1.1.0.1
Summary: Project Subtask Default Display Project
Home-page: https://github.com/sygel-technology/sy-project
Author: Sygel, Odoo Community Association (OCA)
Author-email: support@odoo-community.org
License: AGPL-3
Classifier: Programming Language :: Python
Classifier: Framework :: Odoo
Classifier: Framework :: Odoo :: 16.0
Classifier: License :: OSI Approved :: GNU Affero General Public License v3
Requires-Python: >=3.10
Requires-Dist: odoo-addon-base-view-inheritance-extension<16.1dev,>=16.0dev
Requires-Dist: odoo<16.1dev,>=16.0a
